natlinkcore/__init__.py
natlinkcore/_natlink_core.pyi
natlinkcore/callbackhandler.py
natlinkcore/config.py
natlinkcore/gramparser.py
natlinkcore/loader.py
natlinkcore/natlink.pyi
natlinkcore/natlinkpydebug.py
natlinkcore/natlinkstatus.py
natlinkcore/natlinktimer.py
natlinkcore/natlinkutils.py
natlinkcore/nsformat.py
natlinkcore/py.typed
natlinkcore/readwritefile.py
natlinkcore/redirect_output.py
natlinkcore/singleton.py
natlinkcore/tkinter_dialogs.py
natlinkcore/DefaultConfig/_config_instructions.py
natlinkcore/DefaultConfig/_information_config.py
natlinkcore/DefaultConfig/natlink.ini
natlinkcore/SampleMacros/__init__.py
natlinkcore/SampleMacros/_debug_natlink.py
natlinkcore/SampleMacros/_sample7.py
natlinkcore/SampleMacros/_sample_activatedeactivate.py
natlinkcore/SampleMacros/_sample_callback.py
natlinkcore/SampleMacros/_sample_directory_information.py
natlinkcore/SampleMacros/_sample_move_natlinktimer.py
natlinkcore/SampleMacros/_sample_natlinkstatus.py
natlinkcore/SampleMacros/_sample_runmimic.py
natlinkcore/SampleMacros/_samplehypothesis.py
natlinkcore/SampleMacros/OriginalSampleMacros/Index.htm
natlinkcore/SampleMacros/OriginalSampleMacros/_globals.py
natlinkcore/SampleMacros/OriginalSampleMacros/_mouse.py
natlinkcore/SampleMacros/OriginalSampleMacros/_repeatthat.py
natlinkcore/SampleMacros/OriginalSampleMacros/_sample1.py
natlinkcore/SampleMacros/OriginalSampleMacros/_sample2.py
natlinkcore/SampleMacros/OriginalSampleMacros/_sample3.py
natlinkcore/SampleMacros/OriginalSampleMacros/_sample4.py
natlinkcore/SampleMacros/OriginalSampleMacros/_sample5.py
natlinkcore/SampleMacros/OriginalSampleMacros/_sample8.py
natlinkcore/SampleMacros/OriginalSampleMacros/_sample9.py
natlinkcore/SampleMacros/OriginalSampleMacros/_sleeping.py
natlinkcore/SampleMacros/OriginalSampleMacros/excel_sample7.py
natlinkcore/SampleMacros/OriginalSampleMacros/natspeak_sample6.py
natlinkcore/SampleMacros/OriginalSampleMacros/trainuser.py
natlinkcore-5.4.1.dist-info/entry_points.txt
natlinkcore-5.4.1.dist-info/WHEEL
natlinkcore-5.4.1.dist-info/METADATA
natlinkcore-5.4.1.dist-info/RECORD
