Metadata-Version: 2.1
Name: natlinkcore
Version: 5.4.1
Summary: Python portion of Natlink, a compatibility module for Dragon Naturally Speaking
Author-email: "Quintijn Hoogenboom (maintainer)" <q.hoogenboom@antenna.nl>
Requires-Python: >=3.9
Classifier: Development Status :: 4 - Beta
Classifier: Environment :: Win32 (MS Windows)
Classifier: Intended Audience :: Developers
Classifier: Operating System :: Microsoft :: Windows
Classifier: Programming Language :: Python :: 3.9
Classifier: Programming Language :: Python :: Implementation :: CPython
Classifier: Topic :: Multimedia :: Sound/Audio :: Speech
Classifier: Topic :: Software Development :: Libraries :: Python Modules
Requires-Dist: FreeSimpleGUI>=5.1.0
Requires-Dist: pydebugstring >= 1.0.0.1
Requires-Dist: dtactions>=1.6.3
Requires-Dist: platformdirs >= 4.2.0
Requires-Dist: pyenvutils ; extra == "dev"
Requires-Dist: entry-point-inspector ; extra == "dev"
Requires-Dist: build ; extra == "dev"
Requires-Dist: pytest >=7.1.2 ; extra == "test"
Project-URL: Home, https://github.com/dictation-toolbox/natlinkcore/
Provides-Extra: dev
Provides-Extra: test
